bakplane/__init__.py
bakplane/bakplane_pb2.py
bakplane/bakplane_pb2_grpc.py
bakplane/client.py
bakplane/errors.py
bakplane/symbology.py
bakplane/utils.py
bakplane/extensions/__init__.py
bakplane/extensions/base/__init__.py
bakplane/extensions/modifiers/__init__.py
bakplane/extensions/modifiers/dating.py
bakplane/extensions/spark/__init__.py
bakplane/extensions/spark/utils.py
bakplane/extensions/spark/stores/__init__.py
bakplane/extensions/spark/stores/jdbc.py
bakplane/extensions/spark/stores/postgres.py
bakplane/extensions/spark/stores/redshift.py
bakplane/ingestion/__init__.py
bakplane/ingestion/emitter.py
bakplane/ingestion/landing_zone.py
bakplane/ingestion/models.py
bakplane_python_sdk-1.81.0.data/scripts/bp_generate_initial_migrations.py
bakplane_python_sdk-1.81.0.dist-info/LICENSE
bakplane_python_sdk-1.81.0.dist-info/METADATA
bakplane_python_sdk-1.81.0.dist-info/WHEEL
bakplane_python_sdk-1.81.0.dist-info/top_level.txt
bakplane_python_sdk-1.81.0.dist-info/RECORD
