Metadata-Version: 2.1
Name: bakplane-python-sdk
Version: 1.81.0
Summary: A Python Client for Bakplane
Home-page: https://github.com/openaristos/bakplane-python-sdk
Author: Aristos Data, LLC.
Author-email: hello@openaristos.io
License: AGPLv3
Keywords: open aristos
Platform: UNKNOWN
Classifier: Development Status :: 5 - Production/Stable
Classifier: License :: OSI Approved :: GNU Affero General Public License v3 or later (AGPLv3+)
Classifier: Topic :: Scientific/Engineering :: Information Analysis
Classifier: Topic :: Scientific/Engineering :: Artificial Intelligence
Classifier: Intended Audience :: Financial and Insurance Industry
Classifier: Intended Audience :: Developers
Classifier: Intended Audience :: Healthcare Industry
Classifier: Intended Audience :: Information Technology
Classifier: Intended Audience :: Science/Research
Classifier: Intended Audience :: Telecommunications Industry
Classifier: Programming Language :: Python
Classifier: Programming Language :: Python :: 3
Classifier: Programming Language :: Python :: 3.4
Classifier: Programming Language :: Python :: 3.5
Classifier: Programming Language :: Python :: 3.6
Classifier: Programming Language :: Python :: 3.7
Classifier: Programming Language :: Python :: 3.8
Requires-Dist: grpcio
Requires-Dist: grpcio-tools
Requires-Dist: protobuf
Requires-Dist: SQLAlchemy
Requires-Dist: sqlalchemy-redshift
Requires-Dist: psycopg2-binary
Requires-Dist: farmhashpy
Requires-Dist: boto3
Requires-Dist: dominus-python-sdk (>=0.24.0)
Requires-Dist: click
Requires-Dist: pandas
Requires-Dist: cachetools
Requires-Dist: python-stdnum
Requires-Dist: sortedcontainers
Requires-Dist: certifi
